manga109api/__init__.py
manga109api/manga109api.py
tests/__init__.py
tests/test_data_type.py
tests/test_func.py
manga109api-0.3.1.dist-info/LICENSE
manga109api-0.3.1.dist-info/METADATA
manga109api-0.3.1.dist-info/WHEEL
manga109api-0.3.1.dist-info/top_level.txt
manga109api-0.3.1.dist-info/RECORD
