Metadata-Version: 2.1
Name: manga109api
Version: 0.3.1
Summary: Simple python API to read annotation data of Manga109
Home-page: https://github.com/manga109/manga109api
Author: Yusuke Matsui
Author-email: matsui528@gmail.com
License: MIT
Platform: UNKNOWN
